butcher/__init__.py
butcher/address.py
butcher/buildfile.py
butcher/buildfile_context.py
butcher/cache.py
butcher/error.py
butcher/gitrepo.py
butcher/main.py
butcher/notes.md
butcher/rubygems.py
butcher/util.py
butcher/util_test.py
butcher/target_context/__init__.py
butcher/targets/__init__.py
butcher/targets/base.py
butcher/targets/filegroup.py
butcher/targets/gendeb.py
butcher/targets/genrule.py
butcher/targets/genrule_test.py
butcher/targets/pkg_symlink.py
butcher/targets/pkgfilegroup.py
butcher/targets/unimplemented.py
butcher/targets/virtual.py
butcher-0.2.13.dist-info/DESCRIPTION.rst
butcher-0.2.13.dist-info/METADATA
butcher-0.2.13.dist-info/RECORD
butcher-0.2.13.dist-info/WHEEL
butcher-0.2.13.dist-info/entry_points.txt
butcher-0.2.13.dist-info/metadata.json
butcher-0.2.13.dist-info/pbr.json
butcher-0.2.13.dist-info/top_level.txt
