Metadata-Version: 1.0
Name: butcher
Version: 0.2.13
Summary: General-purpose build system for projects spanning multiple git repos
Home-page: https://github.com/benley/butcher
Author: Benjamin Staffin
Author-email: benley@gmail.com
License: Apache-2
Platform: UNKNOWN
